statsbombpy_local/__init__.py
statsbombpy_local/_api.py
statsbombpy_local/_config.py
statsbombpy_local/_public.py
statsbombpy_local/_utils.py
statsbombpy_local/py.typed
statsbombpy_local/sb.py
statsbombpy_local-0.2.1.dist-info/LICENSE
statsbombpy_local-0.2.1.dist-info/METADATA
statsbombpy_local-0.2.1.dist-info/WHEEL
statsbombpy_local-0.2.1.dist-info/RECORD
