Metadata-Version: 2.1
Name: statsbombpy-local
Version: 0.2.1
Summary: statsbombpy uses local open-data
Home-page: https://github.com/tanzhijian/statsbombpy-local
License: MIT
Author: tanzhijian
Author-email: tanzhijianorg@outlook.com
Requires-Python: >=3.10,<4.0
Classifier: License :: OSI Approved :: MIT License
Classifier: Programming Language :: Python :: 3
Classifier: Programming Language :: Python :: 3.10
Classifier: Programming Language :: Python :: 3.11
Classifier: Programming Language :: Python :: 3.12
Requires-Dist: python-dotenv (>=1.0.0,<2.0.0)
Requires-Dist: statsbombpy (>=1.12.0,<2.0.0)
Project-URL: Repository, https://github.com/tanzhijian/statsbombpy-local
